{
    "DesktopAudioDevice1": {
        "prev_ver": 536870914,
        "name": "Audio del escritorio",
        "uuid": "65e82f2c-7a12-4cdf-8d50-e6c80f969287",
        "id": "pulse_output_capture",
        "versioned_id": "pulse_output_capture",
        "settings": {
            "device_id": "default"
        },
        "mixers": 255,
        "sync": 0,
        "flags": 0,
        "volume": 1.0,
        "balance": 0.5,
        "enabled": true,
        "muted": false,
        "push-to-mute": false,
        "push-to-mute-delay": 0,
        "push-to-talk": false,
        "push-to-talk-delay": 0,
        "hotkeys": {
            "libobs.mute": [],
            "libobs.unmute": [],
            "libobs.push-to-mute": [],
            "libobs.push-to-talk": []
        },
        "deinterlace_mode": 0,
        "deinterlace_field_order": 0,
        "monitoring_type": 0,
        "private_settings": {}
    },
    "current_scene": "Escena",
    "current_program_scene": "Escena",
    "scene_order": [
        {
            "name": "Escena"
        }
    ],
    "name": "Sin Título",
    "sources": [
        {
            "prev_ver": 536870914,
            "name": "Escena",
            "uuid": "75c18d38-5037-4e9c-8c33-4d31f7fca19f",
            "id": "scene",
            "versioned_id": "scene",
            "settings": {
                "id_counter": 3,
                "custom_size": false,
                "items": [
                    {
                        "name": "Captura de pantalla (XSHM)",
                        "source_uuid": "4f05c984-3843-41fb-bbe2-4ec968f3005a",
                        "visible": true,
                        "locked": false,
                        "rot": 0.0,
                        "scale_ref": {
                            "x": 1366.0,
                            "y": 768.0
                        },
                        "align": 5,
                        "bounds_type": 0,
                        "bounds_align": 0,
                        "bounds_crop": false,
                        "crop_left": 0,
                        "crop_top": 0,
                        "crop_right": 0,
                        "crop_bottom": 0,
                        "id": 1,
                        "group_item_backup": false,
                        "pos": {
                            "x": 0.0,
                            "y": 0.0
                        },
                        "pos_rel": {
                            "x": -1.7786458730697632,
                            "y": -1.0
                        },
                        "scale": {
                            "x": 1.0,
                            "y": 1.0
                        },
                        "scale_rel": {
                            "x": 1.0,
                            "y": 1.0
                        },
                        "bounds": {
                            "x": 0.0,
                            "y": 0.0
                        },
                        "bounds_rel": {
                            "x": 0.0,
                            "y": 0.0
                        },
                        "scale_filter": "disable",
                        "blend_method": "default",
                        "blend_type": "normal",
                        "show_transition": {
                            "duration": 0
                        },
                        "hide_transition": {
                            "duration": 0
                        },
                        "private_settings": {}
                    },
                    {
                        "name": "Video Capture Device (PipeWire) (BETA)",
                        "source_uuid": "25e51fd8-ee6f-45b2-9560-acbd91cdffa2",
                        "visible": true,
                        "locked": false,
                        "rot": 0.0,
                        "scale_ref": {
                            "x": 1366.0,
                            "y": 768.0
                        },
                        "align": 5,
                        "bounds_type": 0,
                        "bounds_align": 0,
                        "bounds_crop": false,
                        "crop_left": 0,
                        "crop_top": 0,
                        "crop_right": 0,
                        "crop_bottom": 0,
                        "id": 2,
                        "group_item_backup": false,
                        "pos": {
                            "x": 0.0,
                            "y": 0.0
                        },
                        "pos_rel": {
                            "x": -1.7786458730697632,
                            "y": -1.0
                        },
                        "scale": {
                            "x": 1.0,
                            "y": 1.0
                        },
                        "scale_rel": {
                            "x": 1.0,
                            "y": 1.0
                        },
                        "bounds": {
                            "x": 0.0,
                            "y": 0.0
                        },
                        "bounds_rel": {
                            "x": 0.0,
                            "y": 0.0
                        },
                        "scale_filter": "disable",
                        "blend_method": "default",
                        "blend_type": "normal",
                        "show_transition": {
                            "duration": 0
                        },
                        "hide_transition": {
                            "duration": 0
                        },
                        "private_settings": {}
                    },
                    {
                        "name": "Video Capture Device (V4L2)",
                        "source_uuid": "7dd94163-8c4b-4407-8f53-59a1f4756213",
                        "visible": true,
                        "locked": false,
                        "rot": 0.0,
                        "scale_ref": {
                            "x": 1366.0,
                            "y": 768.0
                        },
                        "align": 5,
                        "bounds_type": 0,
                        "bounds_align": 0,
                        "bounds_crop": false,
                        "crop_left": 0,
                        "crop_top": 0,
                        "crop_right": 0,
                        "crop_bottom": 0,
                        "id": 3,
                        "group_item_backup": false,
                        "pos": {
                            "x": 465.0,
                            "y": 507.0
                        },
                        "pos_rel": {
                            "x": -0.5677083134651184,
                            "y": 0.3203125
                        },
                        "scale": {
                            "x": -0.32499998807907104,
                            "y": 0.32499998807907104
                        },
                        "scale_rel": {
                            "x": -0.32499998807907104,
                            "y": 0.32499998807907104
                        },
                        "bounds": {
                            "x": 0.0,
                            "y": 0.0
                        },
                        "bounds_rel": {
                            "x": 0.0,
                            "y": 0.0
                        },
                        "scale_filter": "disable",
                        "blend_method": "default",
                        "blend_type": "normal",
                        "show_transition": {
                            "duration": 0
                        },
                        "hide_transition": {
                            "duration": 0
                        },
                        "private_settings": {}
                    }
                ]
            },
            "mixers": 0,
            "sync": 0,
            "flags": 0,
            "volume": 1.0,
            "balance": 0.5,
            "enabled": true,
            "muted": false,
            "push-to-mute": false,
            "push-to-mute-delay": 0,
            "push-to-talk": false,
            "push-to-talk-delay": 0,
            "hotkeys": {
                "OBSBasic.SelectScene": [],
                "libobs.show_scene_item.1": [],
                "libobs.hide_scene_item.1": [],
                "libobs.show_scene_item.2": [],
                "libobs.hide_scene_item.2": [],
                "libobs.show_scene_item.3": [],
                "libobs.hide_scene_item.3": []
            },
            "deinterlace_mode": 0,
            "deinterlace_field_order": 0,
            "monitoring_type": 0,
            "canvas_uuid": "6c69626f-6273-4c00-9d88-c5136d61696e",
            "private_settings": {}
        },
        {
            "prev_ver": 536870914,
            "name": "Captura de pantalla (XSHM)",
            "uuid": "4f05c984-3843-41fb-bbe2-4ec968f3005a",
            "id": "xshm_input_v2",
            "versioned_id": "xshm_input_v2",
            "settings": {
                "screen": 0
            },
            "mixers": 0,
            "sync": 0,
            "flags": 0,
            "volume": 1.0,
            "balance": 0.5,
            "enabled": true,
            "muted": false,
            "push-to-mute": false,
            "push-to-mute-delay": 0,
            "push-to-talk": false,
            "push-to-talk-delay": 0,
            "hotkeys": {},
            "deinterlace_mode": 0,
            "deinterlace_field_order": 0,
            "monitoring_type": 0,
            "private_settings": {}
        },
        {
            "prev_ver": 536870914,
            "name": "Video Capture Device (PipeWire) (BETA)",
            "uuid": "25e51fd8-ee6f-45b2-9560-acbd91cdffa2",
            "id": "pipewire-camera-source",
            "versioned_id": "pipewire-camera-source",
            "settings": {},
            "mixers": 0,
            "sync": 0,
            "flags": 0,
            "volume": 1.0,
            "balance": 0.5,
            "enabled": true,
            "muted": false,
            "push-to-mute": false,
            "push-to-mute-delay": 0,
            "push-to-talk": false,
            "push-to-talk-delay": 0,
            "hotkeys": {},
            "deinterlace_mode": 0,
            "deinterlace_field_order": 0,
            "monitoring_type": 0,
            "private_settings": {}
        },
        {
            "prev_ver": 536870914,
            "name": "Video Capture Device (V4L2)",
            "uuid": "7dd94163-8c4b-4407-8f53-59a1f4756213",
            "id": "v4l2_input",
            "versioned_id": "v4l2_input",
            "settings": {
                "device_id": "/dev/video0",
                "input": 0,
                "pixelformat": 1196444237,
                "Power Line Frequency": 2,
                "Saturation": 65,
                "Gamma": 100,
                "White Balance Temperature": 4544,
                "Sharpness": 3,
                "Backlight Compensation": 1,
                "Auto Exposure": 3
            },
            "mixers": 0,
            "sync": 0,
            "flags": 0,
            "volume": 1.0,
            "balance": 0.5,
            "enabled": true,
            "muted": false,
            "push-to-mute": false,
            "push-to-mute-delay": 0,
            "push-to-talk": false,
            "push-to-talk-delay": 0,
            "hotkeys": {},
            "deinterlace_mode": 0,
            "deinterlace_field_order": 0,
            "monitoring_type": 0,
            "private_settings": {}
        }
    ],
    "groups": [],
    "quick_transitions": [],
    "transitions": [],
    "saved_projectors": [],
    "canvases": [],
    "current_transition": "Fade",
    "transition_duration": 300,
    "preview_locked": false,
    "scaling_enabled": false,
    "scaling_level": -11,
    "scaling_off_x": 0.0,
    "scaling_off_y": 0.0,
    "modules": {
        "scripts-tool": [],
        "output-timer": {
            "streamTimerHours": 0,
            "streamTimerMinutes": 0,
            "streamTimerSeconds": 30,
            "recordTimerHours": 0,
            "recordTimerMinutes": 0,
            "recordTimerSeconds": 30,
            "autoStartStreamTimer": false,
            "autoStartRecordTimer": false,
            "pauseRecordTimer": true
        },
        "auto-scene-switcher": {
            "interval": 300,
            "non_matching_scene": "",
            "switch_if_not_matching": false,
            "active": false,
            "switches": []
        }
    },
    "version": 2
}